composetools.py
composetools-0.5.0.dist-info/LICENSE
composetools-0.5.0.dist-info/WHEEL
composetools-0.5.0.dist-info/METADATA
composetools-0.5.0.dist-info/RECORD
