Metadata-Version: 2.1
Name: composetools
Version: 0.5.0
Summary: Utility functions for common tasks when composing functions.
License: ISC
Author: SeparateRecords
Author-email: me@rob.ac
Requires-Python: >=3.8,<4.0
Classifier: License :: OSI Approved
Classifier: Programming Language :: Python :: 3
Classifier: Programming Language :: Python :: 3.8
